hashversion/__init__.py
hashversion/cli.py
hashversion-0.4.0.dist-info/entry_points.txt
hashversion-0.4.0.dist-info/LICENSE
hashversion-0.4.0.dist-info/WHEEL
hashversion-0.4.0.dist-info/METADATA
hashversion-0.4.0.dist-info/RECORD
