Metadata-Version: 2.1
Name: hashversion
Version: 0.4.0
Summary: Automate versioning and related requirements when using hashver
Home-page: https://github.com/miniscruff/hashversion-python
Keywords: versioning,CLI,changelogs
Author: Ronnie Smith
Author-email: halfpint1170@gmail.com
Requires-Python: >=3.6,<4.0
Classifier: Programming Language :: Python :: 3
Classifier: Programming Language :: Python :: 3.6
Classifier: Programming Language :: Python :: 3.7
Classifier: Programming Language :: Python :: 3.8
Classifier: Topic :: Software Development :: Build Tools
Provides-Extra: docs
Requires-Dist: click (>=7.0,<8.0)
Requires-Dist: gitpython (>=3.0.5,<4.0.0)
Requires-Dist: m2r (>=0.2.1,<0.3.0); extra == "docs"
Requires-Dist: sphinx (>=2.3.1,<3.0.0); extra == "docs"
Requires-Dist: sphinx-rtd-theme (>=0.4.3,<0.5.0); extra == "docs"
Requires-Dist: toml (>=0.10.0,<0.11.0)
Project-URL: Repository, https://github.com/miniscruff/hashversion-python
